{
  "name": "design-incremental-execution",
  "status": "approved",
  "created": "2026-01-31",
  "updated": "2026-01-31",
  "author": "plan-agent",
  "version": "1.0.0",
  "files": {
    "requirements": "requirements.md",
    "design": "design.md",
    "tasks": "tasks.md",
    "summary": "summary.md",
    "meta": "meta.yaml"
  },
  "phases": [
    "Foundation",
    "Command Definition Updates",
    "Checkpoint Integration",
    "Interactive Checkpoints",
    "Auto-generation",
    "Linear Integration",
    "Implement Integration"
  ],
  "tasks": [
    {
      "id": "T001",
      "title": "Extend parseFlags() for string type",
      "status": "pending",
      "assignee": null
    },
    {
      "id": "T002",
      "title": "Add flags section to design.md",
      "status": "pending",
      "assignee": null
    },
    {
      "id": "T003",
      "title": "Update preview to show checkpoint status",
      "status": "pending",
      "assignee": null
    },
    {
      "id": "T004",
      "title": "Add summary.md and spec.json to output list",
      "status": "pending",
      "assignee": null
    },
    {
      "id": "T005",
      "title": "Add --dry-run exit logic",
      "status": "pending",
      "assignee": null
    },
    {
      "id": "T006",
      "title": "Add checkpoint load at start of /design",
      "status": "pending",
      "assignee": null
    },
    {
      "id": "T007",
      "title": "Add checkpoint save after RESEARCH",
      "status": "pending",
      "assignee": null
    },
    {
      "id": "T008",
      "title": "Add checkpoint save after WRITE",
      "status": "pending",
      "assignee": null
    },
    {
      "id": "T009",
      "title": "Add --phase flag handling",
      "status": "pending",
      "assignee": null
    },
    {
      "id": "T010",
      "title": "Add --resume flag handling",
      "status": "pending",
      "assignee": null
    },
    {
      "id": "T011",
      "title": "Implement pre-design checkpoint",
      "status": "pending",
      "assignee": null
    },
    {
      "id": "T012",
      "title": "Implement post-design checkpoint",
      "status": "pending",
      "assignee": null
    },
    {
      "id": "T013",
      "title": "Add --no-checkpoint flag handling",
      "status": "pending",
      "assignee": null
    },
    {
      "id": "T014",
      "title": "Auto-generate summary.md",
      "status": "pending",
      "assignee": null
    },
    {
      "id": "T015",
      "title": "Auto-generate spec.json",
      "status": "pending",
      "assignee": null
    },
    {
      "id": "T016",
      "title": "Read integrations.json for Linear config",
      "status": "pending",
      "assignee": null
    },
    {
      "id": "T017",
      "title": "Create Linear issue via MCP",
      "status": "pending",
      "assignee": null
    },
    {
      "id": "T018",
      "title": "Store Linear identifier in spec.json",
      "status": "pending",
      "assignee": null
    },
    {
      "id": "T019",
      "title": "Display Linear issue link",
      "status": "pending",
      "assignee": null
    },
    {
      "id": "T020",
      "title": "Update /implement to read summary.md",
      "status": "pending",
      "assignee": null
    },
    {
      "id": "T021",
      "title": "Update /implement to read spec.json",
      "status": "pending",
      "assignee": null
    },
    {
      "id": "T022",
      "title": "Auto-generate meta.yaml",
      "status": "pending",
      "assignee": null
    }
  ]
}
